{
  "$schema": "../_schema.json",
  "format": "pptx",
  "element": "slide",
  "parent": "presentation",
  "operations": {
    "add": true,
    "set": true,
    "get": true,
    "query": true,
    "remove": true
  },
  "paths": {
    "positional": ["/slide[N]"]
  },
  "note": "Slide layouts are resolved by name via ResolveSlideLayout. 'title' / 'text' shorthand inserts title / content text shapes at Add time. Background accepts hex color, 'transparent', or 'image:/path'. Transition 'morph...' auto-prefixes shape names. Newly added slides contain no placeholders by default — use --prop title=... / text=... shorthand, `add /slide[N] --type placeholder --prop phType=title`, or `add /slide[N] --type shape|textbox` to add content.",
  "properties": {
    "layout": {
      "type": "string",
      "description": "slide layout name (e.g. 'Title Slide', 'Title and Content'). Resolved against the presentation's slide masters.",
      "add": true, "set": true, "get": true,
      "examples": ["--prop layout=\"Title Slide\""],
      "readback": "layout name string",
      "enforcement": "report"
    },
    "title": {
      "type": "string",
      "description": "title text. Creates a Title shape at Add time.",
      "add": true, "set": true, "get": true,
      "examples": ["--prop title=\"Introduction\""],
      "readback": "Preview surfaces the title text (not in Format)",
      "enforcement": "report"
    },
    "text": {
      "type": "string",
      "description": "content body text. Creates a Content text shape at Add time.",
      "add": true, "set": false, "get": false,
      "examples": ["--prop text=\"Body text\""],
      "readback": "not surfaced at slide level",
      "enforcement": "report"
    },
    "background": {
      "type": "color",
      "description": "slide background. Accepts hex color, 'transparent', or 'image:/path'.",
      "add": true, "set": true, "get": true,
      "examples": ["--prop background=#FFFFFF"],
      "readback": "resolved background descriptor",
      "enforcement": "report"
    },
    "transition": {
      "type": "string",
      "description": "transition name (fade, push, wipe, morph, etc.). 'morph...' triggers auto-prefixing of shape names.",
      "add": true, "set": true, "get": true,
      "examples": ["--prop transition=fade"],
      "readback": "transition name",
      "enforcement": "report"
    },
    "advanceTime": {
      "type": "number",
      "description": "auto-advance time in milliseconds (integer). e.g. 5000 = 5 seconds.",
      "aliases": ["advancetime"],
      "add": true, "set": true, "get": true,
      "examples": ["--prop advanceTime=5000"],
      "readback": "milliseconds (integer)",
      "enforcement": "report"
    },
    "advanceClick": {
      "type": "bool",
      "description": "advance on click.",
      "aliases": ["advanceclick"],
      "add": true, "set": true, "get": true,
      "examples": ["--prop advanceClick=true"],
      "readback": "true/false",
      "enforcement": "report"
    },
    "notes": {
      "type": "string",
      "description": "slide notes text. Set-only at creation time.",
      "add": false, "set": true, "get": true,
      "examples": ["--prop notes=\"Speaker notes here\""],
      "readback": "notes text when present",
      "enforcement": "report"
    },
    "hidden": {
      "type": "bool",
      "description": "true when the slide is hidden from slideshow (Slide/@show=false). Surfaces only on Get/Query.",
      "add": false, "set": false, "get": true,
      "readback": "true if slide is hidden in slideshow",
      "enforcement": "report"
    },
    "layoutType": {
      "type": "string",
      "description": "slide layout type name as encoded on the underlying SlideLayout (e.g. blank, title, titleOnly, twoContent, obj, txAndObj). Distinct from `layout`, which is the user-facing layout display name.",
      "add": false, "set": false, "get": true,
      "readback": "layout type token from SlideLayout/@type",
      "enforcement": "report"
    },
    "background.alpha":  { "type":"number", "add":false, "set":false, "get":true, "description":"slide background fill alpha as percent (0..100). Surfaces when the resolved fill carries an alpha channel.", "readback":"integer percent 0..100", "enforcement":"report" },
    "background.crop":   { "type":"string", "add":false, "set":false, "get":true, "description":"slide background image crop quad in `l,t,r,b` percent units (CT_RelativeRect).", "readback":"comma-separated `l,t,r,b` quad", "enforcement":"report" },
    "background.mode":   { "type":"string", "add":false, "set":false, "get":true, "description":"slide background image fill mode — `tile` or `center`. Absent for stretch (default).", "readback":"`tile` | `center`", "enforcement":"report" },
    "background.ref":    { "type":"number", "add":false, "set":false, "get":true, "description":"theme background reference index — bgRef/@idx (1001/1002/1003 etc.) when the slide inherits from the theme.", "readback":"integer theme bg ref id", "enforcement":"report" },
    "background.scale":  { "type":"number", "add":false, "set":false, "get":true, "description":"tile-fill scale percent (sx, both axes). Surfaces with background.mode=tile.", "readback":"integer percent", "enforcement":"report" },
    "matchedShapes":     { "type":"number", "add":false, "set":false, "get":true, "description":"morph transition: number of shapes from the previous slide that matched on the current slide.", "readback":"integer match count", "enforcement":"report" },
    "morphMode":         { "type":"string", "add":false, "set":false, "get":true, "description":"morph transition mode (byObject default, or other p:morph @option token).", "readback":"morph mode token", "enforcement":"report" },
    "morphShapes":       { "type":"number", "add":false, "set":false, "get":true, "description":"morph transition: number of candidate shapes considered for matching on this slide.", "readback":"integer candidate count", "enforcement":"report" }
  },
  "children": [
    { "element": "shape",       "pathSegment": "shape",       "cardinality": "0..n" },
    { "element": "table",       "pathSegment": "table",       "cardinality": "0..n" },
    { "element": "chart",       "pathSegment": "chart",       "cardinality": "0..n" },
    { "element": "picture",     "pathSegment": "picture",     "cardinality": "0..n" },
    { "element": "placeholder", "pathSegment": "placeholder", "cardinality": "0..n" }
  ]
}
